<?xml version="1.0" encoding="utf-8" ?>
<Levels>
  <Level scene="level1.scene" radio_music="radio01.ogg" ambient_music="battle_bg_01.ogg" ambient_battle="bgbattle01.ogg">
    <AircraftNumber>20</AircraftNumber>
    <AircraftFighter>20</AircraftFighter>
    <AircraftBomber>0</AircraftBomber>
    <AircraftTorpedo>0</AircraftTorpedo>
    <AircraftAssult>0</AircraftAssult>
    <AircraftScout>0</AircraftScout>
  </Level>
  <Level scene="level2.scene" radio_music="radio02.ogg" ambient_music="battle_bg_02.ogg" ambient_battle="bgbattle02.ogg">
    <AircraftNumber>25</AircraftNumber>
    <AircraftFighter>20</AircraftFighter>
    <AircraftBomber>5</AircraftBomber>
    <AircraftTorpedo>0</AircraftTorpedo>
    <AircraftAssult>0</AircraftAssult>
    <AircraftScout>0</AircraftScout>
  </Level>
  <Level scene="level3.scene" radio_music="radio03.ogg" ambient_music="battle_bg_03.ogg"  ambient_battle="bgbattle03.ogg">
    <AircraftNumber>28</AircraftNumber>
    <AircraftFighter>20</AircraftFighter>
    <AircraftBomber>8</AircraftBomber>
    <AircraftTorpedo>0</AircraftTorpedo>
    <AircraftAssult>0</AircraftAssult>
    <AircraftScout>0</AircraftScout>
  </Level>
</Levels>
